<?xml version="1.0" encoding="utf-8"?>
<!DOCTYPE hibernate-mapping PUBLIC "-//Hibernate/Hibernate Mapping DTD 3.0//EN"
"http://hibernate.sourceforge.net/hibernate-mapping-3.0.dtd">
<!-- 
    Mapping file autogenerated by MyEclipse Persistence Tools
-->
<hibernate-mapping>
    <class name="com.stpl.pms.hibernate.mapping.StTxnRequestMasterPoker12" table="st_txn_request_master_poker_12" >
        <id name="pokerId" type="java.lang.Long">
            <column name="poker_id" />
            <generator class="native"></generator>
        </id>
        <property name="playerId" type="java.lang.Long">
            <column name="player_id" not-null="true" />
        </property>    
        <property name="transactionId" type="java.lang.Long">
        	<column name="transaction_id"></column>
        </property>
        <property name="actionId" type="java.lang.Long">
            <column name="action_id" not-null="true" />
        </property>
        <property name="tableId" type="java.lang.Long">
            <column name="table_tournament_id" not-null="true" />
        </property>
        <property name="amount" type="java.lang.Double">
            <column name="amount" precision="20" scale="4" not-null="true" />
        </property>
        <property name="reqStatus" type="java.lang.String">
            <column name="req_status" length="7" not-null="true" />
        </property>
        <property name="reqTime" type="java.lang.String">
            <column name="req_time" length="50" not-null="true" />
        </property>
        <property name="txnType" type="java.lang.String">
        	<column name="txn_type" length="50"></column>
        </property>
        <property name="pokerStatus" type="java.lang.String">
        	<column name="poker_status" length="100"></column>
        </property>
    </class>
</hibernate-mapping>
