<?xml version="1.0" encoding="utf-8"?>
<!DOCTYPE hibernate-mapping PUBLIC "-//Hibernate/Hibernate Mapping DTD 3.0//EN"
"http://hibernate.sourceforge.net/hibernate-mapping-3.0.dtd">
<!-- 
    Mapping file autogenerated by MyEclipse Persistence Tools
-->
<hibernate-mapping>
    <class name="com.stpl.pms.hibernate.mapping.StTxnPlrSubwalletMasterPoker" table="st_txn_plr_subwallet_master_poker">
        <id name="id" type="java.lang.Long">
            <column name="id" />
            <generator class="native"></generator>
        </id>
        <property name="playerId" type="java.lang.Long">
            <column name="player_id" not-null="true" />
        </property>
        <property name="domainId" type="java.lang.Short">
            <column name="domain_id" not-null="true" />
        </property>
        <property name="aliasId" type="java.lang.Short">
            <column name="alias_id" not-null="true" />
        </property>
        <property name="actionId" type="java.lang.Long">
            <column name="action_id" not-null="true" />
        </property>
        <property name="gameGroup" type="java.lang.String">
            <column name="game_group" length="6" not-null="true" />
        </property>
        <property name="vendorId" type="java.lang.Short">
            <column name="vendor_id" not-null="true" />
        </property>
        <property name="subWalletTblId" type="java.lang.String">
            <column name="subWallet_tbl_id" length="30" not-null="true" />
        </property>
        <property name="currencyId" type="java.lang.Integer">
            <column name="currency_id" not-null="true" />
        </property>
        <property name="amount" type="java.lang.Double">
            <column name="amount" precision="20" scale="4" not-null="true" />
        </property>
        <property name="status" type="java.lang.String">
            <column name="status" length="8" not-null="true" />
        </property>
        <property name="subWalletTime" type="java.lang.String">
            <column name="subWallet_time" length="50" not-null="true" />
        </property>
        <property name="subWalletUniqueId" type="java.lang.String">
            <column name="subWallet_unique_id" length="100" not-null="true" />
        </property>
    </class>
</hibernate-mapping>
